yurymultiplier/__init__.py
yurymultiplier/yurymultiplier.py
yurymultiplier-0.0.4.dist-info/METADATA
yurymultiplier-0.0.4.dist-info/WHEEL
yurymultiplier-0.0.4.dist-info/top_level.txt
yurymultiplier-0.0.4.dist-info/RECORD
