Metadata-Version: 2.1
Name: yurymultiplier
Version: 0.0.4
Summary: multiply 2 numbers
Author: Yury Moskaltsov
Author-email: yury-m@hotmail.com
Classifier: Programming Language :: Python :: 3
Classifier: License :: OSI Approved :: MIT License
Classifier: Operating System :: OS Independent
Requires-Python: >=3.6
